sklearnk/__init__.py
sklearnk/program1.py
sklearnk/program10.py
sklearnk/program11.py
sklearnk/program12.py
sklearnk/program13.py
sklearnk/program14.py
sklearnk/program15.py
sklearnk/program2.py
sklearnk/program3.py
sklearnk/program4.py
sklearnk/program5.py
sklearnk/program6.py
sklearnk/program7.py
sklearnk/program8.py
sklearnk/program9.py
sklearnk-0.5.1.dist-info/METADATA
sklearnk-0.5.1.dist-info/WHEEL
sklearnk-0.5.1.dist-info/top_level.txt
sklearnk-0.5.1.dist-info/RECORD
