Metadata-Version: 2.4
Name: sklearnk
Version: 0.5.1
Summary: Internal system processing utility library
Author: CoreDev
Author-email: CoreDev <dev@internal.sys>
Requires-Dist: numpy
Requires-Dist: matplotlib
Requires-Dist: scikit-learn
Dynamic: author
